<annotation>
	<folder>7753-8502</folder>
	<filename>007955</filename>
	<path>C:\Users\Administrator\Desktop\7753-8502\7753-8502\007955.jpg</path>
	<source>
		<database>Unknown</database>
	</source>
	<size>
		<width>6600</width>
		<height>4400</height>
		<depth>1</depth>
	</size>
	<segmented>0</segmented>
	<object>
		<name>2</name>
		<pose>Unspecified</pose>
		<truncated>0</truncated>
		<difficult>0</difficult>
		<bndbox>
			<xmin>4989</xmin>
			<ymin>789</ymin>
			<xmax>6282</xmax>
			<ymax>1353</ymax>
		</bndbox>
	</object>
	<object>
		<name>2</name>
		<pose>Unspecified</pose>
		<truncated>1</truncated>
		<difficult>0</difficult>
		<bndbox>
			<xmin>5425</xmin>
			<ymin>2896</ymin>
			<xmax>6600</xmax>
			<ymax>3887</ymax>
		</bndbox>
	</object>
	<object>
		<name>1</name>
		<pose>Unspecified</pose>
		<truncated>0</truncated>
		<difficult>0</difficult>
		<bndbox>
			<xmin>4525</xmin>
			<ymin>2267</ymin>
			<xmax>4718</xmax>
			<ymax>2567</ymax>
		</bndbox>
	</object>
	<object>
		<name>1</name>
		<pose>Unspecified</pose>
		<truncated>0</truncated>
		<difficult>0</difficult>
		<bndbox>
			<xmin>4632</xmin>
			<ymin>2461</ymin>
			<xmax>4818</xmax>
			<ymax>2789</ymax>
		</bndbox>
	</object>
	<object>
		<name>1</name>
		<pose>Unspecified</pose>
		<truncated>0</truncated>
		<difficult>0</difficult>
		<bndbox>
			<xmin>3232</xmin>
			<ymin>2467</ymin>
			<xmax>3575</xmax>
			<ymax>2953</ymax>
		</bndbox>
	</object>
	<object>
		<name>1</name>
		<pose>Unspecified</pose>
		<truncated>0</truncated>
		<difficult>0</difficult>
		<bndbox>
			<xmin>1775</xmin>
			<ymin>396</ymin>
			<xmax>1996</xmax>
			<ymax>746</ymax>
		</bndbox>
	</object>
	<object>
		<name>1</name>
		<pose>Unspecified</pose>
		<truncated>0</truncated>
		<difficult>0</difficult>
		<bndbox>
			<xmin>4532</xmin>
			<ymin>867</ymin>
			<xmax>4746</xmax>
			<ymax>1182</ymax>
		</bndbox>
	</object>
	<object>
		<name>3</name>
		<pose>Unspecified</pose>
		<truncated>0</truncated>
		<difficult>0</difficult>
		<bndbox>
			<xmin>1011</xmin>
			<ymin>317</ymin>
			<xmax>1125</xmax>
			<ymax>439</ymax>
		</bndbox>
	</object>
	<object>
		<name>4</name>
		<pose>Unspecified</pose>
		<truncated>0</truncated>
		<difficult>0</difficult>
		<bndbox>
			<xmin>1339</xmin>
			<ymin>224</ymin>
			<xmax>1703</xmax>
			<ymax>589</ymax>
		</bndbox>
	</object>
	<object>
		<name>4</name>
		<pose>Unspecified</pose>
		<truncated>0</truncated>
		<difficult>0</difficult>
		<bndbox>
			<xmin>1896</xmin>
			<ymin>2174</ymin>
			<xmax>2182</xmax>
			<ymax>2459</ymax>
		</bndbox>
	</object>
	<object>
		<name>3</name>
		<pose>Unspecified</pose>
		<truncated>0</truncated>
		<difficult>0</difficult>
		<bndbox>
			<xmin>1574</xmin>
			<ymin>2217</ymin>
			<xmax>1696</xmax>
			<ymax>2360</ymax>
		</bndbox>
	</object>
	<object>
		<name>4</name>
		<pose>Unspecified</pose>
		<truncated>0</truncated>
		<difficult>0</difficult>
		<bndbox>
			<xmin>1168</xmin>
			<ymin>2610</ymin>
			<xmax>1475</xmax>
			<ymax>2946</ymax>
		</bndbox>
	</object>
	<object>
		<name>5</name>
		<pose>Unspecified</pose>
		<truncated>1</truncated>
		<difficult>0</difficult>
		<bndbox>
			<xmin>6032</xmin>
			<ymin>1453</ymin>
			<xmax>6600</xmax>
			<ymax>2334</ymax>
		</bndbox>
	</object>
</annotation>
